tratatez/__init__.py
tratatez/tratadocu_1.py
tratatez/tratadocu_2.py
tratatez/tratadocu_3.py
tratatez/metodos_de_apoyo/__init__.py
tratatez/metodos_de_apoyo/c_apoyo.py
tratatez-1.5.dist-info/licenses/license.txt
tratatez-1.5.dist-info/METADATA
tratatez-1.5.dist-info/WHEEL
tratatez-1.5.dist-info/top_level.txt
tratatez-1.5.dist-info/RECORD
