Metadata-Version: 2.4
Name: tratatez
Version: 1.5
Summary: Librería para manipulación avanzada de archivos de texto .txt con proposito educativo... enfocada, para construir y simular una consola (preferiblemente utilizando el comando match de python)
Home-page: https://github.com/Jesu-super-galactico/tratatez
Author: El Señor es el único eterno. Que la ciencia lo honre a Él.
Author-email: from.colombia.to.all@gmail.com
License: MPL-2.0
Classifier: Programming Language :: Python :: 3
Classifier: License :: OSI Approved :: Mozilla Public License 2.0 (MPL 2.0)
Requires-Python: >=3.11.3
License-File: license.txt
Dynamic: author
Dynamic: author-email
Dynamic: classifier
Dynamic: description
Dynamic: description-content-type
Dynamic: home-page
Dynamic: license
Dynamic: license-file
Dynamic: requires-python
Dynamic: summary
